string_formatter/__init__.py
string_formatter-1.1.0.dist-info/DESCRIPTION.rst
string_formatter-1.1.0.dist-info/LICENSE.txt
string_formatter-1.1.0.dist-info/METADATA
string_formatter-1.1.0.dist-info/RECORD
string_formatter-1.1.0.dist-info/WHEEL
string_formatter-1.1.0.dist-info/metadata.json
string_formatter-1.1.0.dist-info/namespace_packages.txt
string_formatter-1.1.0.dist-info/top_level.txt
